goshawk/__init__.py
goshawk/adapters/base_adapter.py
goshawk/adapters/duckdb_adapter.py
goshawk/adapters/snowflake_adapter.py
goshawk/controller/deploy.py
goshawk/controller/refresh.py
goshawk/controller/status.py
goshawk/domain/__init__.py
goshawk/domain/exception.py
goshawk/domain/file_reader.py
goshawk/domain/model.py
goshawk/logging.py
goshawk/main.py
goshawk/models/dummy.txt
goshawk/models/mydatabase/schema_a/_schema.yml
goshawk/models/mydatabase/schema_a/model_a1.sql
goshawk/models/mydatabase/schema_a/model_a2.sql
goshawk/models/mydatabase/schema_b/model_b1.sql
goshawk/models/mydatabase/schema_b/model_b2.sql
goshawk/settings.py
goshawk/utils.py
goshawk/visuals/view_tree.py
goshawk-0.0.1.12.dist-info/LICENSE
goshawk-0.0.1.12.dist-info/METADATA
goshawk-0.0.1.12.dist-info/WHEEL
goshawk-0.0.1.12.dist-info/entry_points.txt
goshawk-0.0.1.12.dist-info/RECORD
