Metadata-Version: 2.1
Name: goshawk
Version: 0.0.1.12
Summary: A tool for managing SQL Models
Home-page: https://github.com/ebrassell/goshawk
Author: Eric Brassell
Author-email: erb123@gmail.com
Requires-Python: >=3.10,<3.12
Classifier: Programming Language :: Python :: 3
Classifier: Programming Language :: Python :: 3.10
Classifier: Programming Language :: Python :: 3.11
Requires-Dist: duckdb (==1.0)
Requires-Dist: loguru (>=0.7.2,<0.8.0)
Requires-Dist: pydantic-settings (>=2.2.1,<3.0.0)
Requires-Dist: pyyaml (>=6.0.1,<7.0.0)
Requires-Dist: snowflake-connector-python (>=3.10.0,<4.0.0)
Requires-Dist: sqlglot (>=23.0.5,<24.0.0)
Requires-Dist: tabulate (>=0.9.0,<0.10.0)
Requires-Dist: typer (>=0.9.0,<0.10.0)
Requires-Dist: typing-extensions (>=4.10.0,<5.0.0)
Project-URL: Documentation, https://ebrassell.github.io/goshawk/
Project-URL: Repository, https://github.com/ebrassell/goshawk
